doxx/__init__.py
doxx/app.py
doxx/settings.py
doxx/commands/__init__.py
doxx/commands/browse.py
doxx/commands/build.py
doxx/commands/clean.py
doxx/commands/make.py
doxx/commands/pack.py
doxx/commands/pull.py
doxx/commands/pullkey.py
doxx/commands/repoupdate.py
doxx/commands/search.py
doxx/commands/unpack.py
doxx/commands/whatis.py
doxx/datatypes/__init__.py
doxx/datatypes/cache.py
doxx/datatypes/github.py
doxx/datatypes/key.py
doxx/datatypes/package.py
doxx/datatypes/remotefiles.py
doxx/datatypes/template.py
doxx/renderer/__init__.py
doxx/renderer/inkpy2.py
doxx/renderer/inkpy3.py
doxx/utilities/__init__.py
doxx/utilities/filesystem.py
doxx/utilities/fuzzysearch.py
doxx-0.9.4.data/scripts/doxx
doxx-0.9.4.dist-info/DESCRIPTION.rst
doxx-0.9.4.dist-info/entry_points.txt
doxx-0.9.4.dist-info/METADATA
doxx-0.9.4.dist-info/pydist.json
doxx-0.9.4.dist-info/RECORD
doxx-0.9.4.dist-info/top_level.txt
doxx-0.9.4.dist-info/WHEEL
