Metadata-Version: 2.0
Name: doxx
Version: 0.9.4
Summary: A Simple, Flexible Text Templating, Build, & Project Distribution System
Home-page: http://doxx.org
Author: Christopher Simpkins
Author-email: git.simpkins@gmail.com
License: MIT license
Keywords: build,compile,text,template,templates,templating,scaffold,framework,project,tar.gz,zip,key,documents,text files
Platform: any
Classifier: Intended Audience :: End Users/Desktop
Classifier: Development Status :: 4 - Beta
Classifier: Natural Language :: English
Classifier: License :: OSI Approved :: MIT License
Classifier: Programming Language :: Python
Classifier: Programming Language :: Python :: 2
Classifier: Programming Language :: Python :: 3
Classifier: Operating System :: MacOS :: MacOS X
Classifier: Operating System :: POSIX
Classifier: Operating System :: Unix
Classifier: Operating System :: Microsoft :: Windows
Requires-Dist: Naked
